{
    "contentVersion":  "1.0.0.0",
    "$schema":  "https://schema.management.azure.com/schemas/2019-04-01/deploymentTemplate.json#",
    "resources":  [
                      {
                          "id":  "[concat(resourceId('Microsoft.OperationalInsights/workspaces/providers', parameters('workspace'), 'Microsoft.SecurityInsights'),'/alertRules/862bcf83-d6f8-42b4-a36a-85139db2d3d8')]",
                          "name":  "[concat(parameters('workspace'),'/Microsoft.SecurityInsights/862bcf83-d6f8-42b4-a36a-85139db2d3d8')]",
                          "type":  "Microsoft.OperationalInsights/workspaces/providers/alertRules",
                          "kind":  "Scheduled",
                          "apiVersion":  "2023-12-01-preview",
                          "properties":  {
                                             "displayName":  "Vectra - Risky User Detected - [WC-BASE]",
                                             "description":  "This rule is used to get alerts from Vectra related to users flagged as risky.",
                                             "severity":  "Medium",
                                             "enabled":  true,
                                             "query":  "VectraEntityScoring\r\n| where Severity != \"Low\"",
                                             "queryFrequency":  "PT1H",
                                             "queryPeriod":  "PT1H",
                                             "triggerOperator":  "GreaterThan",
                                             "triggerThreshold":  0,
                                             "suppressionDuration":  "PT5H",
                                             "suppressionEnabled":  false,
                                             "startTimeUtc":  null,
                                             "tactics":  [
                                                             "InitialAccess",
                                                             "Persistence",
                                                             "PrivilegeEscalation",
                                                             "DefenseEvasion",
                                                             "LateralMovement"
                                                         ],
                                             "techniques":  [
                                                                "T1078",
                                                                "T0859"
                                                            ],
                                             "subTechniques":  [

                                                               ],
                                             "alertRuleTemplateName":  null,
                                             "incidentConfiguration":  {
                                                                           "createIncident":  true,
                                                                           "groupingConfiguration":  {
                                                                                                         "enabled":  false,
                                                                                                         "reopenClosedIncident":  false,
                                                                                                         "lookbackDuration":  "PT5H",
                                                                                                         "matchingMethod":  "AllEntities",
                                                                                                         "groupByEntities":  [

                                                                                                                             ],
                                                                                                         "groupByAlertDetails":  [

                                                                                                                                 ],
                                                                                                         "groupByCustomDetails":  [

                                                                                                                                  ]
                                                                                                     }
                                                                       },
                                             "eventGroupingSettings":  {
                                                                           "aggregationKind":  "SingleAlert"
                                                                       },
                                             "alertDetailsOverride":  {
                                                                          "alertDynamicProperties":  [

                                                                                                     ]
                                                                      },
                                             "customDetails":  {

                                                               },
                                             "entityMappings":  null,
                                             "sentinelEntitiesMappings":  null,
                                             "templateVersion":  null
                                         }
                      }
                  ],
    "parameters":  {
                       "workspace":  {
                                         "type":  "String"
                                     }
                   }
}